py4web/__init__.py
py4web/__main__.py
py4web/core.py
py4web/assets/py4web.app._dashboard.zip
py4web/assets/py4web.app._default.zip
py4web/assets/py4web.app._documentation.zip
py4web/assets/py4web.app._minimal.zip
py4web/assets/py4web.app._scaffold.zip
py4web/assets/py4web.app.showcase.zip
py4web/server_adapters/__init__.py
py4web/server_adapters/adapter_gevent.py
py4web/server_adapters/adapter_gevent_websockets.py
py4web/server_adapters/adapter_gunicorn_gevent.py
py4web/server_adapters/adapter_rocket3.py
py4web/server_adapters/adapter_wsgiref.py
py4web/server_adapters/logging_utils.py
py4web/utils/__init__.py
py4web/utils/auth.py
py4web/utils/cors.py
py4web/utils/dbstore.py
py4web/utils/downloader.py
py4web/utils/factories.py
py4web/utils/form.py
py4web/utils/grid.py
py4web/utils/hcaptcha.py
py4web/utils/jsonrpc.py
py4web/utils/mailer.py
py4web/utils/misc.py
py4web/utils/param.py
py4web/utils/populate.py
py4web/utils/publisher.py
py4web/utils/recaptcha.py
py4web/utils/security.py
py4web/utils/tags.py
py4web/utils/url_signer.py
py4web/utils/auth_plugins/__init__.py
py4web/utils/auth_plugins/basic_auth_plugin.py
py4web/utils/auth_plugins/email_auth_plugin.py
py4web/utils/auth_plugins/ldap_plugin.py
py4web/utils/auth_plugins/oauth2discord.py
py4web/utils/auth_plugins/oauth2facebook.py
py4web/utils/auth_plugins/oauth2github.py
py4web/utils/auth_plugins/oauth2google.py
py4web/utils/auth_plugins/oauth2google_scoped.py
py4web/utils/auth_plugins/oauth2okta.py
py4web/utils/auth_plugins/oauth2server.py
py4web/utils/auth_plugins/oauth2wpminiorange.py
py4web/utils/auth_plugins/pam.py
py4web/utils/auth_plugins/pam_plugin.py
py4web/utils/auth_plugins/saml2_plugin.py
py4web/utils/auth_plugins/x509_auth_plugin.py
py4web-1.20260120.1.dist-info/licenses/LICENSE.md
py4web-1.20260120.1.dist-info/METADATA
py4web-1.20260120.1.dist-info/WHEEL
py4web-1.20260120.1.dist-info/entry_points.txt
py4web-1.20260120.1.dist-info/top_level.txt
py4web-1.20260120.1.dist-info/RECORD
