Metadata-Version: 2.4
Name: py4web
Version: 1.20260120.1
Summary: A fast, stable, comprehensive web framework
Author-email: Massimo Di Pierro <massimo.dipierro@gmail.com>
License: Copyright 2017, Massimo Di Pierro
Project-URL: Homepage, https://github.com/web2py/py4web
Project-URL: Bug Tracker, https://github.com/web2py/py4web/issues
Project-URL: Documentation, https://py4web.com
Requires-Python: >=3.9
License-File: LICENSE.md
Requires-Dist: wheel
Requires-Dist: ombott>=2.4
Requires-Dist: click
Requires-Dist: colorama
Requires-Dist: cryptography
Requires-Dist: pathspec
Requires-Dist: portalocker
Requires-Dist: tornado
Requires-Dist: renoir>=1.4.0
Requires-Dist: requests
Requires-Dist: threadsafevariable>=20250716.1
Requires-Dist: pyjwt>=2.0.1
Requires-Dist: pycryptodome
Requires-Dist: pluralize>=20250901.2
Requires-Dist: rocket3>=20241225.1
Requires-Dist: yatl>=20230507.3
Requires-Dist: pydal>=20260118.1
Requires-Dist: watchgod>=0.6
Provides-Extra: test
Requires-Dist: pytest; extra == "test"
Requires-Dist: pytest-cov; extra == "test"
Requires-Dist: mechanize==0.4.6; extra == "test"
Requires-Dist: python-memcached; extra == "test"
Provides-Extra: docs
Requires-Dist: docutils; extra == "docs"
Requires-Dist: pystemmer>=2.2; extra == "docs"
Requires-Dist: sphinx; extra == "docs"
Requires-Dist: sphinx-tabs; extra == "docs"
Requires-Dist: sphinx_rtd_theme; extra == "docs"
Requires-Dist: rinohtype==0.5.4; extra == "docs"
Requires-Dist: sphinxcontrib-spelling; extra == "docs"
Provides-Extra: manage
Requires-Dist: twine; extra == "manage"
Dynamic: license-file
